setup.py
django_rest_test_data.egg-info/PKG-INFO
django_rest_test_data.egg-info/SOURCES.txt
django_rest_test_data.egg-info/dependency_links.txt
django_rest_test_data.egg-info/requires.txt
django_rest_test_data.egg-info/top_level.txt
rest_test_data/__init__.py
rest_test_data/models.py
rest_test_data/urls.py
rest_test_data/views.py
rest_test_data/__pycache__/__init__.cpython-32.pyc
rest_test_data/__pycache__/__init__.cpython-33.pyc
rest_test_data/__pycache__/models.cpython-32.pyc
rest_test_data/__pycache__/models.cpython-33.pyc
rest_test_data/__pycache__/urls.cpython-32.pyc
rest_test_data/__pycache__/urls.cpython-33.pyc
rest_test_data/__pycache__/views.cpython-32.pyc
rest_test_data/__pycache__/views.cpython-33.pyc
rest_test_data/tests/__init__.py
rest_test_data/tests/test_base.py
rest_test_data/tests/test_rest.py
rest_test_data/tests/test_views.py
rest_test_data/tests/__pycache__/__init__.cpython-32.pyc
rest_test_data/tests/__pycache__/__init__.cpython-33.pyc
rest_test_data/tests/__pycache__/test_base.cpython-32.pyc
rest_test_data/tests/__pycache__/test_base.cpython-33.pyc
rest_test_data/tests/__pycache__/test_rest.cpython-32.pyc
rest_test_data/tests/__pycache__/test_rest.cpython-33.pyc
rest_test_data/tests/__pycache__/test_views.cpython-32.pyc
rest_test_data/tests/__pycache__/test_views.cpython-33.pyc