Metadata-Version: 1.0
Name: django-rest-test-data
Version: 0.2.0
Summary: Django app that exposes an API that lets you put the database in any (legal) desired state.
Home-page: http://github.com/hogarthww/django-rest-test-data
Author: Hogarth Worldwide Ltd.
Author-email: zonza-devs@hogarthww.com
License: GPLv2
Platform: UNKNOWN
